{
  "video_info": {
    "name": "1e8d4bbe-234c-4610-9093-95d40ea50f33.avi",
    "path": "C:\\Users\\T2520847\\P3\\Codes\\Thesis V5\\NeSy\\Apply Video\\1e8d4bbe-234c-4610-9093-95d40ea50f33.avi",
    "file_size_mb": 507.78173828125,
    "frames_processed": 9096
  },
  "detections_summary": {
    "yolo": {
      "total_detections": 145,
      "average_confidence": 0.6992961973979556,
      "min_confidence": 0.5007038116455078,
      "max_confidence": 0.876961886882782,
      "frames_with_detections": 144,
      "stable_tracks": 0
    },
    "rtdetr": {
      "total_detections": 430,
      "average_confidence": 0.6020283047543016,
      "min_confidence": 0.4004056751728058,
      "max_confidence": 0.921274721622467,
      "frames_with_detections": 419,
      "stable_tracks": 0
    },
    "medsam": {
      "total_detections": 518,
      "average_confidence": 0.8409749034749034,
      "min_confidence": 0.62890625,
      "max_confidence": 0.94140625,
      "frames_with_detections": 502,
      "stable_tracks": 0
    }
  },
  "segmentations_summary": {
    "medsam": {
      "frames_with_segmentation": 3207,
      "avg_mask_shape": "unknown"
    }
  },
  "consensus_voting": {
    "polyp_present": true,
    "overall_confidence": 0.8862234320477279,
    "consensus_frame_count": 53,
    "consensus_percentage": 0.5826737027264731,
    "num_consensus_runs": 1,
    "average_confidence_boost": 0.028668549282911626,
    "models_detected": 3,
    "yolo_detected": true,
    "rtdetr_detected": true,
    "medsam_detected": true,
    "frame_level_consensus_count": 379,
    "border_filtered_count": 338
  },
  "symbolic_reasoning_summary": {
    "total_analyzed": 1,
    "high_risk_count": 0,
    "medium_risk_count": 0,
    "low_risk_count": 1,
    "consensus_polyp_count": 1,
    "polyp_type_counts": {
      "LIFTED_POLYP": 1
    },
    "error_count": 0,
    "_temporal_consensus": {
      "tracks": [
        {
          "polyp_id": 1,
          "start_frame": 5705,
          "end_frame": 5851,
          "num_frames": 53,
          "frame_sequence": [
            5705,
            5706,
            5707,
            5708,
            5709,
            5710,
            5711,
            5712,
            5713,
            5714,
            5715,
            5716,
            5717,
            5718,
            5719,
            5720,
            5721,
            5722,
            5723,
            5724,
            5725,
            5726,
            5727,
            5728,
            5729,
            5730,
            5731,
            5733,
            5735,
            5828,
            5829,
            5830,
            5831,
            5832,
            5833,
            5834,
            5835,
            5836,
            5837,
            5838,
            5839,
            5840,
            5841,
            5842,
            5843,
            5844,
            5845,
            5846,
            5847,
            5848,
            5849,
            5850,
            5851
          ],
          "confidences": [
            0.9364275336265564,
            0.931928296883901,
            0.9349570473035177,
            0.9334424336751302,
            0.9290796319643656,
            0.930822491645813,
            0.9300017555554708,
            0.930452565352122,
            0.9318375587463379,
            0.9326874415079752,
            0.9349658687909445,
            0.9294854998588562,
            0.9311853845914205,
            0.9296973347663879,
            0.9293252428372701,
            0.9203380147616068,
            0.926112949848175,
            0.9308096965154012,
            0.8874492049217224,
            0.8510906100273132,
            0.8615874648094177,
            0.8202034831047058,
            0.8063894708951315,
            0.8565074801445007,
            0.792965034643809,
            0.7048687040805817,
            0.6865027050177256,
            0.6430884798367819,
            0.8318673372268677
          ],
          "original_average_conf": 0.9364275336265564,
          "temporal_average_conf": 0.8862234320477279,
          "confidence_boost": -0.05725247421483892,
          "box": [
            451.68384222417956,
            512.2390344261667,
            705.0608602355721,
            962.8850330630482
          ],
          "all_boxes": [
            [
              451.59006754557294,
              506.9634094238281,
              702.4481404622396,
              957.2667439778646
            ],
            [
              451.9533996582031,
              507.481689453125,
              705.1915690104166,
              957.5075073242188
            ],
            [
              451.54004923502606,
              503.7117614746094,
              705.4502970377604,
              957.1432698567709
            ],
            [
              451.3895568847656,
              502.8703308105469,
              705.9301147460938,
              955.5144653320312
            ],
            [
              451.568115234375,
              502.70631917317706,
              706.8061726888021,
              955.7366129557291
            ],
            [
              451.5364583333333,
              502.7880147298177,
              706.3218383789062,
              956.4428507486979
            ],
            [
              451.38670857747394,
              502.6001790364583,
              707.1450602213541,
              955.3486124674479
            ],
            [
              452.0773111979167,
              503.54297892252606,
              706.1892903645834,
              955.5718180338541
            ],
            [
              452.21954345703125,
              503.7315165201823,
              706.0900472005209,
              955.8373006184896
            ],
            [
              452.2133483886719,
              504.4390563964844,
              705.0470174153646,
              958.631591796875
            ],
            [
              452.09812418619794,
              505.4823913574219,
              704.9065144856771,
              959.8182373046875
            ],
            [
              451.6622823079427,
              508.00318400065106,
              704.3982340494791,
              959.0975952148438
            ],
            [
              452.1868591308594,
              509.36255900065106,
              705.1718953450521,
              959.2849527994791
            ],
            [
              452.1480000813802,
              510.1400553385417,
              704.9295247395834,
              960.0473429361979
            ],
            [
              452.20069376627606,
              510.5513102213542,
              705.2438761393229,
              959.25732421875
            ],
            [
              452.36769612630206,
              510.8418782552083,
              706.9311116536459,
              961.0421142578125
            ],
            [
              452.1568298339844,
              510.3754069010417,
              707.3386637369791,
              960.9731241861979
            ],
            [
              452.0478108723958,
              510.22681681315106,
              706.6717732747396,
              960.6487426757812
            ],
            [
              452.40733846028644,
              510.2808329264323,
              706.9149983723959,
              960.234619140625
            ],
            [
              452.0544942220052,
              511.22458902994794,
              706.0343017578125,
              960.9893188476562
            ],
            [
              452.1912434895833,
              511.7898356119792,
              706.0235392252604,
              962.0027262369791
            ],
            [
              452.3618977864583,
              511.17828369140625,
              706.1759440104166,
              961.7432250976562
            ],
            [
              452.41274007161456,
              510.5751037597656,
              706.0383911132812,
              961.2706502278646
            ],
            [
              452.07663981119794,
              509.8398132324219,
              705.8990681966146,
              961.1283976236979
            ],
            [
              452.3430684407552,
              529.2909749348959,
              702.0062662760416,
              961.5239054361979
            ],
            [
              452.497314453125,
              523.194580078125,
              702.0669555664062,
              970.5539347330729
            ],
            [
              452.47522989908856,
              522.8685913085938,
              702.4502156575521,
              965.7518310546875
            ],
            [
              452.6005147298177,
              523.1123453776041,
              700.3023885091146,
              963.62158203125
            ],
            [
              451.37782796223956,
              512.9072672526041,
              695.8914388020834,
              969.406982421875
            ]
          ],
          "merged_from": 2,
          "frame": 5705,
          "confidence_sequence": [
            0.8862234320477279
          ],
          "frame_confidence_pairs": [
            [
              5705,
              0.8862234320477279
            ],
            [
              5706,
              0.8862234320477279
            ],
            [
              5707,
              0.8862234320477279
            ],
            [
              5708,
              0.8862234320477279
            ],
            [
              5709,
              0.8862234320477279
            ],
            [
              5710,
              0.8862234320477279
            ],
            [
              5711,
              0.8862234320477279
            ],
            [
              5712,
              0.8862234320477279
            ],
            [
              5713,
              0.8862234320477279
            ],
            [
              5714,
              0.8862234320477279
            ],
            [
              5715,
              0.8862234320477279
            ],
            [
              5716,
              0.8862234320477279
            ],
            [
              5717,
              0.8862234320477279
            ],
            [
              5718,
              0.8862234320477279
            ],
            [
              5719,
              0.8862234320477279
            ],
            [
              5720,
              0.8862234320477279
            ],
            [
              5721,
              0.8862234320477279
            ],
            [
              5722,
              0.8862234320477279
            ],
            [
              5723,
              0.8862234320477279
            ],
            [
              5724,
              0.8862234320477279
            ],
            [
              5725,
              0.8862234320477279
            ],
            [
              5726,
              0.8862234320477279
            ],
            [
              5727,
              0.8862234320477279
            ],
            [
              5728,
              0.8862234320477279
            ],
            [
              5729,
              0.8862234320477279
            ],
            [
              5730,
              0.8862234320477279
            ],
            [
              5731,
              0.8862234320477279
            ],
            [
              5733,
              0.8862234320477279
            ],
            [
              5735,
              0.8862234320477279
            ],
            [
              5828,
              0.8862234320477279
            ],
            [
              5829,
              0.8862234320477279
            ],
            [
              5830,
              0.8862234320477279
            ],
            [
              5831,
              0.8862234320477279
            ],
            [
              5832,
              0.8862234320477279
            ],
            [
              5833,
              0.8862234320477279
            ],
            [
              5834,
              0.8862234320477279
            ],
            [
              5835,
              0.8862234320477279
            ],
            [
              5836,
              0.8862234320477279
            ],
            [
              5837,
              0.8862234320477279
            ],
            [
              5838,
              0.8862234320477279
            ],
            [
              5839,
              0.8862234320477279
            ],
            [
              5840,
              0.8862234320477279
            ],
            [
              5841,
              0.8862234320477279
            ],
            [
              5842,
              0.8862234320477279
            ],
            [
              5843,
              0.8862234320477279
            ],
            [
              5844,
              0.8862234320477279
            ],
            [
              5845,
              0.8862234320477279
            ],
            [
              5846,
              0.8862234320477279
            ],
            [
              5847,
              0.8862234320477279
            ],
            [
              5848,
              0.8862234320477279
            ],
            [
              5849,
              0.8862234320477279
            ],
            [
              5850,
              0.8862234320477279
            ],
            [
              5851,
              0.8862234320477279
            ]
          ],
          "representative_frame": 5705,
          "representative_confidence": 0.8862234320477279
        }
      ],
      "total_polyp_instances": 1,
      "total_frame_coverage": 53,
      "average_confidence_boost": 0.028668549282911626
    },
    "temporal_aggregation": {
      "total_tracks": 1,
      "total_track_frames": 53,
      "average_confidence_boost": 0.028668549282911626
    },
    "rules_applied": [
      "Rule1_MedSAM2Hybrid",
      "Rule2_Consensus",
      "Rule3_ClinicalSplit",
      "Rule4_SSLFeatures",
      "Rule5_BorderFilter",
      "TemporalAveraging"
    ],
    "results": [
      {
        "polyp_id": 1,
        "frame": 5721,
        "classification": "LOW_RISK",
        "expert_classification": "LOW_RISK",
        "confidence": 0.7302375860676733,
        "symbolic_confidence": 0.7302375860676733,
        "detection_confidence": 0.8862234320477279,
        "clinical_confidence": 0.7302375860676733,
        "ssl_boost_applied": 0.0,
        "consensus": true,
        "model": "temporal_consensus",
        "redness": 0.015280689112842083,
        "texture": 0.2546451220011494,
        "vessel_visibility": 0.0,
        "radius": 0.20237078466828673,
        "polyp_type": "LIFTED_POLYP",
        "polyp_type_confidence": 0.6023015567399779,
        "cluster_id": 6,
        "prediction_source": "ssl_enhanced_cluster_specific",
        "ssl_integrated": true,
        "method": "enhanced_ssl_444dim",
        "num_frames": 53,
        "frame_sequence": [
          5705,
          5706,
          5707,
          5708,
          5709,
          5710,
          5711,
          5712,
          5713,
          5714,
          5715,
          5716,
          5717,
          5718,
          5719,
          5720,
          5721,
          5722,
          5723,
          5724,
          5725,
          5726,
          5727,
          5728,
          5729,
          5730,
          5731,
          5733,
          5735,
          5828,
          5829,
          5830,
          5831,
          5832,
          5833,
          5834,
          5835,
          5836,
          5837,
          5838,
          5839,
          5840,
          5841,
          5842,
          5843,
          5844,
          5845,
          5846,
          5847,
          5848,
          5849,
          5850,
          5851
        ],
        "clinical_class": "ADENOMATOUS_POLYP",
        "clinical_risk": "MEDIUM",
        "clinical_description": "Polypoid lesion \u2014 discrete mucosal protrusion identified"
      }
    ]
  },
  "polyp_features_detail": [
    {
      "polyp_id": 1,
      "frame": 5721,
      "model": "temporal_consensus",
      "consensus": true,
      "redness": 0.015280689112842083,
      "radius": 0.20237078466828673,
      "texture": 0.2546451220011494,
      "vessel_visibility": 0.0,
      "classification": "LOW_RISK",
      "expert_classification": "LOW_RISK",
      "confidence": 0.7302375860676733,
      "symbolic_confidence": 0.7302375860676733,
      "detection_confidence": 0.8862234320477279,
      "clinical_confidence": 0.7302375860676733,
      "risk_score": 0.1106527280635376,
      "polyp_type": "LIFTED_POLYP",
      "polyp_type_confidence": 0.6023015567399779,
      "cluster_id": 6,
      "prediction_source": "ssl_enhanced_cluster_specific",
      "box": [
        450.7020568847656,
        503.38006591796875,
        710.0211181640625,
        961.4138793945312
      ],
      "num_frames": 53,
      "frame_sequence": [
        5705,
        5706,
        5707,
        5708,
        5709,
        5710,
        5711,
        5712,
        5713,
        5714,
        5715,
        5716,
        5717,
        5718,
        5719,
        5720,
        5721,
        5722,
        5723,
        5724,
        5725,
        5726,
        5727,
        5728,
        5729,
        5730,
        5731,
        5733,
        5735,
        5828,
        5829,
        5830,
        5831,
        5832,
        5833,
        5834,
        5835,
        5836,
        5837,
        5838,
        5839,
        5840,
        5841,
        5842,
        5843,
        5844,
        5845,
        5846,
        5847,
        5848,
        5849,
        5850,
        5851
      ],
      "temporal_boost": -0.05725247421483892
    }
  ],
  "processing_timestamp": "2026-06-04T00:13:49.867375",
  "rules_applied": {
    "rule1_medsam_independent": true,
    "rule1_description": "MedSAM uses detector-guided box prompts with point fallback and mask-constrained ROI segmentation",
    "rule2_consensus_voting": true,
    "rule2_description": "Only polyps with continuous multi-frame agreement from all 3 models are accepted",
    "rule3_symbolic_reasoning": true,
    "rule3_description": "Video-level 70-30 split used for symbolic reasoning separation",
    "rule4_ssl_features": true,
    "rule4_description": "444-dimensional SSL features + masked ROI biomarkers integrated into expert decisions",
    "rule5_roi_analysis": true,
    "rule5_description": "Border and background artifacts are excluded by mask-based ROI cropping"
  },
  "video_annotation": "duodenum ulcer",
  "video_level_clinical_class": "LIFTED_POLYP"
}